conjuguer/__init__.py
conjuguer/blank.py
conjuguer/main.py
conjuguer/verbs.py
pnu_conjuguer-0.5.1.data/data/man/man1/conjuguer.1.gz
pnu_conjuguer-0.5.1.data/data/share/locale/en/LC_MESSAGES/conjuguer.mo
pnu_conjuguer-0.5.1.data/data/share/locale/fr/LC_MESSAGES/conjuguer.mo
pnu_conjuguer-0.5.1.dist-info/License
pnu_conjuguer-0.5.1.dist-info/METADATA
pnu_conjuguer-0.5.1.dist-info/WHEEL
pnu_conjuguer-0.5.1.dist-info/entry_points.txt
pnu_conjuguer-0.5.1.dist-info/top_level.txt
pnu_conjuguer-0.5.1.dist-info/RECORD
