Metadata-Version: 2.1
Name: pnu-conjuguer
Version: 0.5.1
Summary: conjugaison des verbes Français
Home-page: https://github.com/HubTou/conjuguer/
Author: Hubert Tournier
Author-email: nobody@nowhere.invalid
License: BSD 3-Clause License
Project-URL: Bug Tracker, https://github.com/HubTou/conjuguer/issues
Keywords: pnu-project
Platform: UNKNOWN
Classifier: Development Status :: 4 - Beta
Classifier: Environment :: Console
Classifier: Intended Audience :: Education
Classifier: Intended Audience :: End Users/Desktop
Classifier: License :: OSI Approved :: BSD License
Classifier: Natural Language :: English
Classifier: Natural Language :: French
Classifier: Operating System :: OS Independent
Classifier: Operating System :: POSIX :: BSD :: FreeBSD
Classifier: Operating System :: Microsoft :: Windows
Classifier: Programming Language :: Python :: 3
Classifier: Programming Language :: Python :: 3.3
Classifier: Programming Language :: Python :: 3.4
Classifier: Programming Language :: Python :: 3.5
Classifier: Programming Language :: Python :: 3.6
Classifier: Programming Language :: Python :: 3.7
Classifier: Programming Language :: Python :: 3.8
Classifier: Programming Language :: Python :: 3.9
Classifier: Programming Language :: Python :: 3.10
Classifier: Topic :: Education
Classifier: Topic :: Education :: Computer Aided Instruction (CAI)
Classifier: Topic :: Text Processing :: Linguistic
Classifier: Topic :: Utilities
Requires-Python: >=3.3
License-File: License
Requires-Dist: colorama
Requires-Dist: dict-fr-AU-DELA
Requires-Dist: dict-fr-ABU
